[
	{
    "id": "allclothes",
	"type": "item_group",
    "subtype": "distribution",
	"copy-from": "allclothes",
	"extend": { 
		"entries": [
			{ "item": "bloomers", "prob": 15 },
			{ "item": "cheongsam", "prob": 30 },
			{ "item": "cheongsam_medium", "prob": 25 },
			{ "item": "cheongsam_short", "prob": 20 },
			{ "item": "socks_long", "prob": 2 },
			{ "item": "tai_chi_pants", "prob": 3 },
			{ "item": "tang_shirt", "prob": 3 },
			{ "item": "tang_suit", "prob": 3 }
		]
	}
	},
	{
    "id": "dollar_clothes",
    "type": "item_group",
	"copy-from": "dollar_clothes",
	"extend": { 
		"items": [ 
			[ "socks_long", 20 ]
		] 
	}
	},
	{
    "id": "donated_clothes",
    "type": "item_group",
    "subtype": "collection",
	"copy-from": "donated_clothes",
	"extend": { 
		"items": [
			{ "item": "socks_long" }
		]
	}
	},
	{
    "id": "dress_shop",
    "type": "item_group",
	"copy-from": "dress_shop",
	"extend": { 
		"items": [ 
			[ "cheongsam", 65 ], 
			[ "cheongsam_medium", 50 ], 
			[ "cheongsam_short", 35 ] 
		] 
	}
	},
	{
    "id": "dresser",
	"type": "item_group",
    "ammo": 50,
    "magazine": 100,
	"copy-from": "dresser",
	"extend": { 
		"items": [ 
			[ "bloomers", 35 ], 
			[ "cheongsam", 35 ], 
			[ "cheongsam_medium", 25 ], 
			[ "cheongsam_short", 15 ],
			[ "socks_long", 25 ],
			[ "tai_chi_pants", 3 ],
			[ "tang_shirt", 3 ],
			[ "tang_suit", 3 ]
		] 
	}
	},
	{
    "id": "dresses",
	"type": "item_group",
	"copy-from": "dresses",
	"extend": { 
		"items": [ 
			[ "cheongsam", 25 ], 
			[ "cheongsam_medium", 18 ], 
			[ "cheongsam_short", 12 ] 
		] 
	}
	},
	{
    "id": "dresses_womens",
	"type": "item_group",
    "subtype": "distribution",
	"copy-from": "dresses_womens",
	"extend": { 
		"items": [ 
			[ "cheongsam", 5 ], 
			[ "cheongsam_medium", 4 ], 
			[ "cheongsam_short", 3 ] 
		] 
	}
	},
	{
    "id": "female_underwear_bottom",
	"type": "item_group",
	"copy-from": "female_underwear_bottom",
	"extend": { 
		"items": [ 
			[ "bloomers", 35 ]
		] 
	}
	},
	{
    "id": "gi",
    "type": "item_group",
	"copy-from": "gi",
	"extend": { 
		"items": [ 
			[ "tai_chi_pants", 25 ],
			[ "tang_shirt", 25 ],
			[ "tang_suit", 25 ]
		] 
	}
	},
	{
    "id": "lab_torso",
	"type": "item_group",
	"copy-from": "lab_torso",
	"extend": { 
		"items": [ 
			[ "cheongsam", 35 ], 
			[ "cheongsam_medium", 25 ], 
			[ "cheongsam_short", 15 ] 
		] 
	}
	},
	{
    "id": "laundry",
	"type": "item_group",
	"copy-from": "laundry",
	"extend": { 
		"items": [ 
			[ "bloomers", 15 ], 
			[ "cheongsam", 30 ], 
			[ "cheongsam_medium", 20 ], 
			[ "cheongsam_short", 10 ],
			[ "socks_long", 2 ]
		] 
	}
	},
	{
    "id": "pants",
	"type": "item_group",
	"copy-from": "pants",
	"extend": { 
		"items": [ 
			[ "cheongsam", 35 ], 
			[ "cheongsam_medium", 25 ], 
			[ "cheongsam_short", 15 ] 
		] 
	}
	},
	{
    "id": "shoestore_accessories",
	"type": "item_group",
	"copy-from": "shoestore_accessories",
	"extend": { 
		"items": [ 
			[ "socks_long", 50 ]
		] 
	}
	},
	{
    "id": "socks_unisex",
    "type": "item_group",
    "//": "unisex socks",
    "subtype": "distribution",
	"copy-from": "socks_unisex",
	"extend": { 
		"items": [ 
			{ "item": "socks_long", "prob": 35 } 
		] 
	}
	},
	{
    "id": "suits_womens",
    "type": "item_group",
    "//": "suits/dresses, full body coverage for women.",
    "subtype": "distribution",
	"copy-from": "suits_womens",
	"extend": { 
		"items": [ 
			[ "cheongsam", 25 ], 
			[ "cheongsam_medium", 20 ], 
			[ "cheongsam_short", 15 ] 
		] 
	}
	},
	{
    "id": "underwear_womens",
    "type": "item_group",
    "//": "womens underwear.",
    "subtype": "distribution",
	"copy-from": "underwear_womens",
	"extend": { 
		"items": [ 
			{ "item": "bloomers", "prob": 35 } 
		] 
	}
	},
	{
    "id": "winter",
	"type": "item_group",
    "ammo": 50,
    "magazine": 100,
	"copy-from": "winter",
	"extend": { 
		"items": [ 
			[ "socks_long", 5 ]
		] 
	}
	}
]
